graphfaker/__init__.py
graphfaker/cli.py
graphfaker/core.py
graphfaker/enums.py
graphfaker/logger.py
graphfaker/utils.py
graphfaker/fetchers/flights.py
graphfaker/fetchers/osm.py
graphfaker/fetchers/wiki.py
graphfaker-0.3.1.dist-info/licenses/AUTHORS.rst
graphfaker-0.3.1.dist-info/licenses/LICENSE
graphfaker-0.3.1.dist-info/METADATA
graphfaker-0.3.1.dist-info/WHEEL
graphfaker-0.3.1.dist-info/top_level.txt
graphfaker-0.3.1.dist-info/RECORD
