Metadata-Version: 2.4
Name: graphfaker
Version: 0.3.1
Summary: an open-source python library for generating, and loading both synthetic and real-world graph datasets
Author-email: Dennis Irorere <denironyx@gmail.com>
Maintainer-email: Dennis Irorere <denironyx@gmail.com>
License-Expression: MIT
Project-URL: bugs, https://github.com/graphgeeks-lab/graphfaker/issues
Project-URL: changelog, https://github.com/graphgeeks-lab/graphfaker/blob/master/changelog.md
Project-URL: homepage, https://github.com/graphgeeks-lab/graphfaker/
Keywords: faker,graph-data,flights,osmnx,graphs,graphfaker
License-File: LICENSE
License-File: AUTHORS.rst
Requires-Dist: faker>=37.1.0
Requires-Dist: networkx>=3.4.2
Requires-Dist: osmnx==2.0.2
Requires-Dist: pandas>=2.2.2
Requires-Dist: requests>=2.32.3
Requires-Dist: typer
Requires-Dist: wikipedia>=1.4.0
Provides-Extra: dev
Requires-Dist: coverage; extra == "dev"
Requires-Dist: mypy; extra == "dev"
Requires-Dist: pytest; extra == "dev"
Requires-Dist: ruff; extra == "dev"
Dynamic: license-file
